<?xml version="1.0" encoding="UTF-8" standalone="no"?>
<TcBusinessDataLocalization xmlns="http://teamcenter.com/BusinessModel/TcBusinessDataLocalization" Date="Tue Nov 02 07:18:21 PM 2021">
    <Add>
   <key id="BusinessObject{::}Sub0SubscriptionProvider" locale="zh_CN" status="Approved">订阅提供程序</key>
   <key id="BusinessObject{::}Sub0NotificationProvider" locale="zh_CN" status="Approved">通知提供程序</key>
   <key id="BusinessObject{::}Sub0SubscribleTypesProvider" locale="zh_CN" status="Approved">可订阅类型提供程序</key>

   <key id="CommandDisplayName{::}Sub0AddFollower" locale="zh_CN" status="Approved">添加关注者</key>
   <key id="CommandDisplayName{::}Sub0AddSubscriptionCriteria" locale="zh_CN" status="Approved">添加</key>
   <key id="CommandDisplayName{::}Sub0CreateObjectTypeSubscription" locale="zh_CN" status="Approved">关注类型</key>
   <key id="CommandDisplayName{::}Sub0DeleteMessage" locale="zh_CN" status="Approved">删除消息</key>
   <key id="CommandDisplayName{::}Sub0DeleteSubscription" locale="zh_CN" status="Approved">删除</key>
   <key id="CommandDisplayName{::}Sub0EditSubscriptionCriteria" locale="zh_CN" status="Approved">编辑</key>
   <key id="CommandDisplayName{::}Sub0SaveAsSubscription" locale="zh_CN" status="Approved">另存为</key>
   <key id="CommandDisplayName{::}Sub0Subscribe" locale="zh_CN" status="Approved">关注</key>
   <key id="CommandDisplayName{::}Sub0TemporaryTransferNotification" locale="zh_CN" status="Approved">传递通知</key>
   <key id="ConditionDescription{::}Sub0CopyCmdCond" locale="zh_CN" status="Approved">该条件总是将 ImanSubscription 对象评估为 false。</key>
   <key id="ConditionDescription{::}Sub0DeleteSubscriptionCmdCond" locale="zh_CN" status="Approved">此条件确定通过的订阅对象是否可删除。</key>
   <key id="ConditionDescription{::}Sub0SaveAsSubscriptionCmdCond" locale="zh_CN" status="Approved">此条件确定通过的订阅对象是否允许另存。</key>
   <key id="ConditionDescription{::}Sub0StartEditTableCmdCond" locale="zh_CN" status="Approved">该条件始终将 ImanSubscription 对象评估为 false。</key>
   <key id="ConditionDescription{::}Sub0TemporaryTransferNotificationCmdCond" locale="zh_CN" status="Approved">此条件确定通过的订阅对象是否允许临时转让。</key>
</Add>
</TcBusinessDataLocalization>
